mycmdb/__init.py__
mycmdb/configure.py
mycmdb/data.py
mycmdb/filesystem.py
mycmdb/production.py
mycmdb/utils.py
mycmdb-0.0.2.dist-info/METADATA
mycmdb-0.0.2.dist-info/WHEEL
mycmdb-0.0.2.dist-info/licenses/LICENSE.txt
mycmdb-0.0.2.dist-info/RECORD
