Metadata-Version: 2.4
Name: mycmdb
Version: 0.0.2
Summary: Simple small personal CMDB for everyone
Project-URL: Homepage, https://github.com/ramongilmoreno/mycmdb
Project-URL: Issues, https://github.com/ramongilmoreno/mycmdb/issues
Author-email: Ramón Gil Moreno <ramongilmoreno@gmail.com>
License-Expression: MIT
License-File: LICENSE.txt
Classifier: Operating System :: OS Independent
Classifier: Programming Language :: Python :: 3
Requires-Python: >=3.9
Requires-Dist: jinja2
